adfs_aws_login/__init__.py
adfs_aws_login/__main__.py
adfs_aws_login/cli.py
adfs_aws_login/conf.py
adfs_aws_login/credentials.py
adfs_aws_login/saml.py
adfs_aws_login-0.2.11.dist-info/LICENSE
adfs_aws_login-0.2.11.dist-info/METADATA
adfs_aws_login-0.2.11.dist-info/WHEEL
adfs_aws_login-0.2.11.dist-info/entry_points.txt
adfs_aws_login-0.2.11.dist-info/top_level.txt
adfs_aws_login-0.2.11.dist-info/RECORD
