Metadata-Version: 2.1
Name: adfs-aws-login
Version: 0.2.11
Summary: CLI login to AWS using ADFS
Home-page: http://github.com/NitorCreations/adfs-aws-login
Author: Pasi Niemi
Author-email: pasi.niemi@nitor.com
License: Apache 2.0
Download-URL: https://github.com/NitorCreations/adfs-aws-login
Platform: UNKNOWN
Requires-Dist: beautifulsoup4 (>=4.8.1)
Requires-Dist: lxml
Requires-Dist: requests (>=2.22.0)
Requires-Dist: threadlocal-aws (>=0.10)
